Workbook

Sheet 📋 Cover
B3: KANGAROO REVENUE COMMAND CENTRE
B4: Audience-Adaptive FP&A Revenue Dashboard · 8-sheet Portfolio Workbook · Portfolio Case Study
B5: Built by Julaluk Clements · CPA (ASA) · halloffrey.com
B9: WORKBOOK NAVIGATION | C9: PURPOSE | D9: AUDIENCE
B11: 📋 Cover | C11: Workbook index, version notes, AI disclosure | D11: All
B12: 📊 Executive Summary | C12: KPI cards, revenue trend, key signals — one-page view | D12: CEO / CFO / Board
B13: 👁 Audience Lens | C13: What each stakeholder cares about and why | D13: FP&A / Finance leads
B14: 📈 Revenue Analysis | C14: Net revenue, ARR/MRR, discount risk, deferred quality | D14: CFO / FP&A / Sales
B15: 🗺 Dashboard Logic | C15: KPI definitions, metric rationale, audience mapping | D15: FP&A / Analysts
B16: ✅ QA Control | C16: Row count, reconciliation checks, integrity flags | D16: Finance / Audit
B17: 📊 Chart Data | C17: Source data tables powering all four embedded charts | D17: Internal / FP&A
B18: 📉 Charts | C18: Monthly Net Revenue, BU mix, ARR/MRR, Discount risk | D18: All / Recruiters
B20: VERSION
B21: Version | C21: 1.0 · Audience-Adaptive Edition
B22: Dataset | C22: 216 rows · Jan 2024 – Dec 2025 · 3 BUs · 3 Products
B23: AI Disclosure | C23: AI-assisted build: code generation and layout acceleration used. Finance logic, KPI selection, audience design, interpretation and final review directed and validated by Julaluk Clements.
B24: Purpose | C24: Portfolio case study demonstrating FP&A revenue analysis, audience-adaptive executive reporting, and finance-led dashboard design.

Sheet 📊 Executive Summary
B2: EXECUTIVE SUMMARY · Revenue Command Centre
B3: Key performance signals across Net Revenue, ARR/MRR, Discount Risk and Deferred Revenue · Jan 2024 – Dec 2025
B5: KPI CARDS · Full Dataset · All Business Units
B7: TOTAL NET REVENUE | C7: TOTAL GROSS REVENUE | D7: TOTAL ARR | E7: AVG DISCOUNT % | F7: DEFERRED REV Δ | G7: RECOGNIZED REVENUE
B8: =SUM('📂 Raw Data'!K2:K217) -> 22598636 | C8: =SUM('📂 Raw Data'!I2:I217) -> 25775590 | D8: =SUM('📂 Raw Data'!N2:N217) -> 2.7118364e+08 | E8: =AVERAGE('📂 Raw Data'!J2:J217) -> 0.11647176 | F8: =SUM('📂 Raw Data'!L2:L217) -> 631937.07 | G8: =SUM('📂 Raw Data'!M2:M217) -> 23230573
B9: 22.6M total — Expansion leads revenue type | C9: 25.8M gross before discount reduction | D9: 271M ARR across 216 data points | E9: 11.6% blended — monitor for margin erosion | F9: Positive deferred — revenue quality intact | G9: 23.2M recognized across full period
B12: NET REVENUE BY BUSINESS UNIT | E12: NET REVENUE BY PRODUCT | G12: NET REVENUE BY SEGMENT
B13: Business Unit | C13: Net Revenue | E13: Product | F13: Net Revenue | G13: Segment | H13: Net Revenue
B14: North America | C14: =SUMIF('📂 Raw Data'!C2:C217,"North America",'📂 Raw Data'!K2:K217) -> 7896687.9 | E14: Product B | F14: =SUMIF('📂 Raw Data'!D2:D217,"Product B",'📂 Raw Data'!K2:K217) -> 8533713.1 | G14: Enterprise | H14: =SUMIF('📂 Raw Data'!F2:F217,"Enterprise",'📂 Raw Data'!K2:K217) -> 7964772.3
B15: APAC | C15: =SUMIF('📂 Raw Data'!C2:C217,"APAC",'📂 Raw Data'!K2:K217) -> 7651525.1 | E15: Product A | F15: =SUMIF('📂 Raw Data'!D2:D217,"Product A",'📂 Raw Data'!K2:K217) -> 7357124.1 | G15: Mid-Market | H15: =SUMIF('📂 Raw Data'!F2:F217,"Mid-Market",'📂 Raw Data'!K2:K217) -> 7521033.3
B16: Europe | C16: =SUMIF('📂 Raw Data'!C2:C217,"Europe",'📂 Raw Data'!K2:K217) -> 7050423.2 | E16: Product C | F16: =SUMIF('📂 Raw Data'!D2:D217,"Product C",'📂 Raw Data'!K2:K217) -> 6707799 | G16: SMB | H16: =SUMIF('📂 Raw Data'!F2:F217,"SMB",'📂 Raw Data'!K2:K217) -> 7112830.6
B18: NET REVENUE BY TYPE | E18: DISCOUNT RISK SIGNAL
B19: Revenue Type | C19: Net Revenue | E19: Blended Avg Discount | F19: =TEXT(AVERAGE('📂 Raw Data'!J2:J217),"0.0%") -> 11.6% | G19: Approaching 12% threshold — monitor quarterly
B20: Expansion | C20: =SUMIF('📂 Raw Data'!E2:E217,"Expansion",'📂 Raw Data'!K2:K217) -> 8419565.5 | E20: High-Discount Segment | F20: SMB | G20: SMB segment carries highest discount exposure
B21: New | C21: =SUMIF('📂 Raw Data'!E2:E217,"New",'📂 Raw Data'!K2:K217) -> 7265090.5 | E21: Expansion Revenue Mix | F21: =TEXT(SUMIF('📂 Raw Data'!E2:E217,"Expansion",'📂 Raw Data'!K2:K217)/SUM('📂 Raw Data'!K2:K217),"0.0%") -> 37.3% | G21: Expansion as top revenue type — healthy signal
B22: Renewal | C22: =SUMIF('📂 Raw Data'!E2:E217,"Renewal",'📂 Raw Data'!K2:K217) -> 6913980.2 | E22: Renewal Risk | F22: =TEXT(SUMIF('📂 Raw Data'!E2:E217,"Renewal",'📂 Raw Data'!K2:K217)/SUM('📂 Raw Data'!K2:K217),"0.0%") -> 30.6% | G22: Renewal mix below 35% — retention strategy needed

Sheet 👁 Audience Lens
B2: AUDIENCE LENS · What Each Stakeholder Needs to See
B3: Audience-adaptive FP&A: same data, different lens, different decision support
B7: 👔 CEO · "Are we growing? Are we at risk?"
B8: KPIs TO SHOW | C8: ANALYTICAL FOCUS | D8: WHAT TO AVOID | E8: SIGNAL COLOUR
B9: • Total Net Revenue • Revenue growth YoY • Expansion vs Renewal mix • Top BU performance | C9: Business momentum and strategic direction. Wants a one-number story with one risk flag. | D9: Do not show discount tables, deferred schedules, or formula detail. | E9: Accent: 00A896
B11: 📊 CFO · "Is revenue quality intact? Where is margin risk?"
B12: KPIs TO SHOW | C12: ANALYTICAL FOCUS | D12: WHAT TO AVOID | E12: SIGNAL COLOUR
B13: • Deferred revenue quality • Discount rate trend • ARR/MRR movement • Recognized vs Gross gap | C13: Revenue integrity, margin protection, and forecast reliability. Wants to see QA signals. | D13: Do not bury discount risk in averages — CFO needs segment-level exposure. | E13: Accent: F0A040
B15: 🧮 FP&A LEAD · "What drives the numbers? Where do I need to reforecast?"
B16: KPIs TO SHOW | C16: ANALYTICAL FOCUS | D16: WHAT TO AVOID | E16: SIGNAL COLOUR
B17: • All KPIs with full segmentation • MoM revenue movement • BU × Product × Segment mix • Deferred Δ trend | C17: Full analytical depth. Needs to explain variances, model scenarios, and brief executives. | D17: Nothing — FP&A consumes all layers. | E17: Accent: 00A896
B19: 🎯 SALES LEADERSHIP · "Which products, segments, and regions are winning?"
B20: KPIs TO SHOW | C20: ANALYTICAL FOCUS | D20: WHAT TO AVOID | E20: SIGNAL COLOUR
B21: • Net Revenue by BU • New vs Expansion vs Renewal split • Product performance ranking • Discount % by segment | C21: Pipeline quality, win rate by segment, and where to focus quota pressure. | D21: Do not show deferred revenue or ARR mechanics — confuses sales narrative. | E21: Accent: F0A040
B23: 🏛 BOARD · "Are we on track? What is the risk to forecast?"
B24: KPIs TO SHOW | C24: ANALYTICAL FOCUS | D24: WHAT TO AVOID | E24: SIGNAL COLOUR
B25: • Total ARR • Net Revenue vs prior period • Discount risk flag • One-line deferred quality note | C25: Strategic confidence. Board wants three numbers and one risk. No operational detail. | D25: No formula detail, no segment tables, no month-by-month data. | E25: Accent: C8D6DF

Sheet 📈 Revenue Analysis
B2: REVENUE ANALYSIS · Net Revenue, ARR/MRR, Discount Risk, Deferred Quality
B5: MONTHLY NET REVENUE TREND · All Business Units
B6: Month | C6: Gross Revenue | D6: Net Revenue | E6: ARR | F6: MRR | G6: Avg Discount % | H6: Deferred Δ | I6: Recognized Rev
B7: 2024-01 | C7: =SUMIFS('📂 Raw Data'!I2:I217,'📂 Raw Data'!B2:B217,B7) -> 759773.83 | D7: =SUMIFS('📂 Raw Data'!K2:K217,'📂 Raw Data'!B2:B217,B7) -> 653003.46 | E7: =SUMIFS('📂 Raw Data'!N2:N217,'📂 Raw Data'!B2:B217,B7) -> 7836041.6 | F7: =SUMIFS('📂 Raw Data'!O2:O217,'📂 Raw Data'!B2:B217,B7) -> 653003.46 | G7: =AVERAGEIFS('📂 Raw Data'!J2:J217,'📂 Raw Data'!B2:B217,B7) -> 0.11867778 | H7: =SUMIFS('📂 Raw Data'!L2:L217,'📂 Raw Data'!B2:B217,B7) -> 14989.52 | I7: =SUMIFS('📂 Raw Data'!M2:M217,'📂 Raw Data'!B2:B217,B7) -> 667992.98
B8: 2024-02 | C8: =SUMIFS('📂 Raw Data'!I2:I217,'📂 Raw Data'!B2:B217,B8) -> 641991.03 | D8: =SUMIFS('📂 Raw Data'!K2:K217,'📂 Raw Data'!B2:B217,B8) -> 583177.6 | E8: =SUMIFS('📂 Raw Data'!N2:N217,'📂 Raw Data'!B2:B217,B8) -> 6998131.2 | F8: =SUMIFS('📂 Raw Data'!O2:O217,'📂 Raw Data'!B2:B217,B8) -> 583177.6 | G8: =AVERAGEIFS('📂 Raw Data'!J2:J217,'📂 Raw Data'!B2:B217,B8) -> 0.097355556 | H8: =SUMIFS('📂 Raw Data'!L2:L217,'📂 Raw Data'!B2:B217,B8) -> 2686.46 | I8: =SUMIFS('📂 Raw Data'!M2:M217,'📂 Raw Data'!B2:B217,B8) -> 585864.05
B9: 2024-03 | C9: =SUMIFS('📂 Raw Data'!I2:I217,'📂 Raw Data'!B2:B217,B9) -> 1151682.1 | D9: =SUMIFS('📂 Raw Data'!K2:K217,'📂 Raw Data'!B2:B217,B9) -> 1059808 | E9: =SUMIFS('📂 Raw Data'!N2:N217,'📂 Raw Data'!B2:B217,B9) -> 12717696 | F9: =SUMIFS('📂 Raw Data'!O2:O217,'📂 Raw Data'!B2:B217,B9) -> 1059808 | G9: =AVERAGEIFS('📂 Raw Data'!J2:J217,'📂 Raw Data'!B2:B217,B9) -> 0.086166667 | H9: =SUMIFS('📂 Raw Data'!L2:L217,'📂 Raw Data'!B2:B217,B9) -> 41833.94 | I9: =SUMIFS('📂 Raw Data'!M2:M217,'📂 Raw Data'!B2:B217,B9) -> 1101641.9
B10: 2024-04 | C10: =SUMIFS('📂 Raw Data'!I2:I217,'📂 Raw Data'!B2:B217,B10) -> 1135182.7 | D10: =SUMIFS('📂 Raw Data'!K2:K217,'📂 Raw Data'!B2:B217,B10) -> 973180.27 | E10: =SUMIFS('📂 Raw Data'!N2:N217,'📂 Raw Data'!B2:B217,B10) -> 11678163 | F10: =SUMIFS('📂 Raw Data'!O2:O217,'📂 Raw Data'!B2:B217,B10) -> 973180.27 | G10: =AVERAGEIFS('📂 Raw Data'!J2:J217,'📂 Raw Data'!B2:B217,B10) -> 0.14396667 | H10: =SUMIFS('📂 Raw Data'!L2:L217,'📂 Raw Data'!B2:B217,B10) -> 43722.63 | I10: =SUMIFS('📂 Raw Data'!M2:M217,'📂 Raw Data'!B2:B217,B10) -> 1016902.9
B11: 2024-05 | C11: =SUMIFS('📂 Raw Data'!I2:I217,'📂 Raw Data'!B2:B217,B11) -> 1064439.3 | D11: =SUMIFS('📂 Raw Data'!K2:K217,'📂 Raw Data'!B2:B217,B11) -> 965325.7 | E11: =SUMIFS('📂 Raw Data'!N2:N217,'📂 Raw Data'!B2:B217,B11) -> 11583908 | F11: =SUMIFS('📂 Raw Data'!O2:O217,'📂 Raw Data'!B2:B217,B11) -> 965325.7 | G11: =AVERAGEIFS('📂 Raw Data'!J2:J217,'📂 Raw Data'!B2:B217,B11) -> 0.0775 | H11: =SUMIFS('📂 Raw Data'!L2:L217,'📂 Raw Data'!B2:B217,B11) -> 16162.46 | I11: =SUMIFS('📂 Raw Data'!M2:M217,'📂 Raw Data'!B2:B217,B11) -> 981488.15
B12: 2024-06 | C12: =SUMIFS('📂 Raw Data'!I2:I217,'📂 Raw Data'!B2:B217,B12) -> 777405.83 | D12: =SUMIFS('📂 Raw Data'!K2:K217,'📂 Raw Data'!B2:B217,B12) -> 692527.11 | E12: =SUMIFS('📂 Raw Data'!N2:N217,'📂 Raw Data'!B2:B217,B12) -> 8310325.4 | F12: =SUMIFS('📂 Raw Data'!O2:O217,'📂 Raw Data'!B2:B217,B12) -> 692527.11 | G12: =AVERAGEIFS('📂 Raw Data'!J2:J217,'📂 Raw Data'!B2:B217,B12) -> 0.1111 | H12: =SUMIFS('📂 Raw Data'!L2:L217,'📂 Raw Data'!B2:B217,B12) -> 26325.99 | I12: =SUMIFS('📂 Raw Data'!M2:M217,'📂 Raw Data'!B2:B217,B12) -> 718853.12
B13: 2024-07 | C13: =SUMIFS('📂 Raw Data'!I2:I217,'📂 Raw Data'!B2:B217,B13) -> 1371764.6 | D13: =SUMIFS('📂 Raw Data'!K2:K217,'📂 Raw Data'!B2:B217,B13) -> 1218456.7 | E13: =SUMIFS('📂 Raw Data'!N2:N217,'📂 Raw Data'!B2:B217,B13) -> 14621481 | F13: =SUMIFS('📂 Raw Data'!O2:O217,'📂 Raw Data'!B2:B217,B13) -> 1218456.7 | G13: =AVERAGEIFS('📂 Raw Data'!J2:J217,'📂 Raw Data'!B2:B217,B13) -> 0.1113 | H13: =SUMIFS('📂 Raw Data'!L2:L217,'📂 Raw Data'!B2:B217,B13) -> -649.53 | I13: =SUMIFS('📂 Raw Data'!M2:M217,'📂 Raw Data'!B2:B217,B13) -> 1217807.2
B14: 2024-08 | C14: =SUMIFS('📂 Raw Data'!I2:I217,'📂 Raw Data'!B2:B217,B14) -> 738981.86 | D14: =SUMIFS('📂 Raw Data'!K2:K217,'📂 Raw Data'!B2:B217,B14) -> 637601.64 | E14: =SUMIFS('📂 Raw Data'!N2:N217,'📂 Raw Data'!B2:B217,B14) -> 7651219.5 | F14: =SUMIFS('📂 Raw Data'!O2:O217,'📂 Raw Data'!B2:B217,B14) -> 637601.64 | G14: =AVERAGEIFS('📂 Raw Data'!J2:J217,'📂 Raw Data'!B2:B217,B14) -> 0.12441111 | H14: =SUMIFS('📂 Raw Data'!L2:L217,'📂 Raw Data'!B2:B217,B14) -> 4066.02 | I14: =SUMIFS('📂 Raw Data'!M2:M217,'📂 Raw Data'!B2:B217,B14) -> 641667.66
B15: 2024-09 | C15: =SUMIFS('📂 Raw Data'!I2:I217,'📂 Raw Data'!B2:B217,B15) -> 1835974.7 | D15: =SUMIFS('📂 Raw Data'!K2:K217,'📂 Raw Data'!B2:B217,B15) -> 1568177.1 | E15: =SUMIFS('📂 Raw Data'!N2:N217,'📂 Raw Data'!B2:B217,B15) -> 18818125 | F15: =SUMIFS('📂 Raw Data'!O2:O217,'📂 Raw Data'!B2:B217,B15) -> 1568177.1 | G15: =AVERAGEIFS('📂 Raw Data'!J2:J217,'📂 Raw Data'!B2:B217,B15) -> 0.1223 | H15: =SUMIFS('📂 Raw Data'!L2:L217,'📂 Raw Data'!B2:B217,B15) -> 46928.9 | I15: =SUMIFS('📂 Raw Data'!M2:M217,'📂 Raw Data'!B2:B217,B15) -> 1615105.9
B16: 2024-10 | C16: =SUMIFS('📂 Raw Data'!I2:I217,'📂 Raw Data'!B2:B217,B16) -> 912231.09 | D16: =SUMIFS('📂 Raw Data'!K2:K217,'📂 Raw Data'!B2:B217,B16) -> 776190.31 | E16: =SUMIFS('📂 Raw Data'!N2:N217,'📂 Raw Data'!B2:B217,B16) -> 9314283.8 | F16: =SUMIFS('📂 Raw Data'!O2:O217,'📂 Raw Data'!B2:B217,B16) -> 776190.31 | G16: =AVERAGEIFS('📂 Raw Data'!J2:J217,'📂 Raw Data'!B2:B217,B16) -> 0.12925556 | H16: =SUMIFS('📂 Raw Data'!L2:L217,'📂 Raw Data'!B2:B217,B16) -> 21344.56 | I16: =SUMIFS('📂 Raw Data'!M2:M217,'📂 Raw Data'!B2:B217,B16) -> 797534.87
B17: 2024-11 | C17: =SUMIFS('📂 Raw Data'!I2:I217,'📂 Raw Data'!B2:B217,B17) -> 959174.15 | D17: =SUMIFS('📂 Raw Data'!K2:K217,'📂 Raw Data'!B2:B217,B17) -> 882368.33 | E17: =SUMIFS('📂 Raw Data'!N2:N217,'📂 Raw Data'!B2:B217,B17) -> 10588420 | F17: =SUMIFS('📂 Raw Data'!O2:O217,'📂 Raw Data'!B2:B217,B17) -> 882368.33 | G17: =AVERAGEIFS('📂 Raw Data'!J2:J217,'📂 Raw Data'!B2:B217,B17) -> 0.087077778 | H17: =SUMIFS('📂 Raw Data'!L2:L217,'📂 Raw Data'!B2:B217,B17) -> 10759.52 | I17: =SUMIFS('📂 Raw Data'!M2:M217,'📂 Raw Data'!B2:B217,B17) -> 893127.83
B18: 2024-12 | C18: =SUMIFS('📂 Raw Data'!I2:I217,'📂 Raw Data'!B2:B217,B18) -> 1248081.6 | D18: =SUMIFS('📂 Raw Data'!K2:K217,'📂 Raw Data'!B2:B217,B18) -> 1104736.4 | E18: =SUMIFS('📂 Raw Data'!N2:N217,'📂 Raw Data'!B2:B217,B18) -> 13256836 | F18: =SUMIFS('📂 Raw Data'!O2:O217,'📂 Raw Data'!B2:B217,B18) -> 1104736.4 | G18: =AVERAGEIFS('📂 Raw Data'!J2:J217,'📂 Raw Data'!B2:B217,B18) -> 0.10112222 | H18: =SUMIFS('📂 Raw Data'!L2:L217,'📂 Raw Data'!B2:B217,B18) -> 13578.94 | I18: =SUMIFS('📂 Raw Data'!M2:M217,'📂 Raw Data'!B2:B217,B18) -> 1118315.3
B19: 2025-01 | C19: =SUMIFS('📂 Raw Data'!I2:I217,'📂 Raw Data'!B2:B217,B19) -> 1199518.8 | D19: =SUMIFS('📂 Raw Data'!K2:K217,'📂 Raw Data'!B2:B217,B19) -> 1051419.4 | E19: =SUMIFS('📂 Raw Data'!N2:N217,'📂 Raw Data'!B2:B217,B19) -> 12617032 | F19: =SUMIFS('📂 Raw Data'!O2:O217,'📂 Raw Data'!B2:B217,B19) -> 1051419.4 | G19: =AVERAGEIFS('📂 Raw Data'!J2:J217,'📂 Raw Data'!B2:B217,B19) -> 0.12586667 | H19: =SUMIFS('📂 Raw Data'!L2:L217,'📂 Raw Data'!B2:B217,B19) -> 74240.55 | I19: =SUMIFS('📂 Raw Data'!M2:M217,'📂 Raw Data'!B2:B217,B19) -> 1125659.9
B20: 2025-02 | C20: =SUMIFS('📂 Raw Data'!I2:I217,'📂 Raw Data'!B2:B217,B20) -> 880586.35 | D20: =SUMIFS('📂 Raw Data'!K2:K217,'📂 Raw Data'!B2:B217,B20) -> 723705.39 | E20: =SUMIFS('📂 Raw Data'!N2:N217,'📂 Raw Data'!B2:B217,B20) -> 8684464.8 | F20: =SUMIFS('📂 Raw Data'!O2:O217,'📂 Raw Data'!B2:B217,B20) -> 723705.39 | G20: =AVERAGEIFS('📂 Raw Data'!J2:J217,'📂 Raw Data'!B2:B217,B20) -> 0.17188889 | H20: =SUMIFS('📂 Raw Data'!L2:L217,'📂 Raw Data'!B2:B217,B20) -> -17854.44 | I20: =SUMIFS('📂 Raw Data'!M2:M217,'📂 Raw Data'!B2:B217,B20) -> 705850.96
B21: 2025-03 | C21: =SUMIFS('📂 Raw Data'!I2:I217,'📂 Raw Data'!B2:B217,B21) -> 1080829.3 | D21: =SUMIFS('📂 Raw Data'!K2:K217,'📂 Raw Data'!B2:B217,B21) -> 963510.9 | E21: =SUMIFS('📂 Raw Data'!N2:N217,'📂 Raw Data'!B2:B217,B21) -> 11562131 | F21: =SUMIFS('📂 Raw Data'!O2:O217,'📂 Raw Data'!B2:B217,B21) -> 963510.9 | G21: =AVERAGEIFS('📂 Raw Data'!J2:J217,'📂 Raw Data'!B2:B217,B21) -> 0.11013333 | H21: =SUMIFS('📂 Raw Data'!L2:L217,'📂 Raw Data'!B2:B217,B21) -> 37243.54 | I21: =SUMIFS('📂 Raw Data'!M2:M217,'📂 Raw Data'!B2:B217,B21) -> 1000754.4
B22: 2025-04 | C22: =SUMIFS('📂 Raw Data'!I2:I217,'📂 Raw Data'!B2:B217,B22) -> 1297154.3 | D22: =SUMIFS('📂 Raw Data'!K2:K217,'📂 Raw Data'!B2:B217,B22) -> 1175868.2 | E22: =SUMIFS('📂 Raw Data'!N2:N217,'📂 Raw Data'!B2:B217,B22) -> 14110418 | F22: =SUMIFS('📂 Raw Data'!O2:O217,'📂 Raw Data'!B2:B217,B22) -> 1175868.2 | G22: =AVERAGEIFS('📂 Raw Data'!J2:J217,'📂 Raw Data'!B2:B217,B22) -> 0.090155556 | H22: =SUMIFS('📂 Raw Data'!L2:L217,'📂 Raw Data'!B2:B217,B22) -> -19347.66 | I22: =SUMIFS('📂 Raw Data'!M2:M217,'📂 Raw Data'!B2:B217,B22) -> 1156520.5
B23: 2025-05 | C23: =SUMIFS('📂 Raw Data'!I2:I217,'📂 Raw Data'!B2:B217,B23) -> 1051122.3 | D23: =SUMIFS('📂 Raw Data'!K2:K217,'📂 Raw Data'!B2:B217,B23) -> 901474.63 | E23: =SUMIFS('📂 Raw Data'!N2:N217,'📂 Raw Data'!B2:B217,B23) -> 10817696 | F23: =SUMIFS('📂 Raw Data'!O2:O217,'📂 Raw Data'!B2:B217,B23) -> 901474.63 | G23: =AVERAGEIFS('📂 Raw Data'!J2:J217,'📂 Raw Data'!B2:B217,B23) -> 0.13092222 | H23: =SUMIFS('📂 Raw Data'!L2:L217,'📂 Raw Data'!B2:B217,B23) -> 61707.28 | I23: =SUMIFS('📂 Raw Data'!M2:M217,'📂 Raw Data'!B2:B217,B23) -> 963181.92
B24: 2025-06 | C24: =SUMIFS('📂 Raw Data'!I2:I217,'📂 Raw Data'!B2:B217,B24) -> 1228352 | D24: =SUMIFS('📂 Raw Data'!K2:K217,'📂 Raw Data'!B2:B217,B24) -> 1086984 | E24: =SUMIFS('📂 Raw Data'!N2:N217,'📂 Raw Data'!B2:B217,B24) -> 13043807 | F24: =SUMIFS('📂 Raw Data'!O2:O217,'📂 Raw Data'!B2:B217,B24) -> 1086984 | G24: =AVERAGEIFS('📂 Raw Data'!J2:J217,'📂 Raw Data'!B2:B217,B24) -> 0.11632222 | H24: =SUMIFS('📂 Raw Data'!L2:L217,'📂 Raw Data'!B2:B217,B24) -> 57337.28 | I24: =SUMIFS('📂 Raw Data'!M2:M217,'📂 Raw Data'!B2:B217,B24) -> 1144321.2
B25: 2025-07 | C25: =SUMIFS('📂 Raw Data'!I2:I217,'📂 Raw Data'!B2:B217,B25) -> 1246763.1 | D25: =SUMIFS('📂 Raw Data'!K2:K217,'📂 Raw Data'!B2:B217,B25) -> 1047121.4 | E25: =SUMIFS('📂 Raw Data'!N2:N217,'📂 Raw Data'!B2:B217,B25) -> 12565457 | F25: =SUMIFS('📂 Raw Data'!O2:O217,'📂 Raw Data'!B2:B217,B25) -> 1047121.4 | G25: =AVERAGEIFS('📂 Raw Data'!J2:J217,'📂 Raw Data'!B2:B217,B25) -> 0.13764444 | H25: =SUMIFS('📂 Raw Data'!L2:L217,'📂 Raw Data'!B2:B217,B25) -> 22746.7 | I25: =SUMIFS('📂 Raw Data'!M2:M217,'📂 Raw Data'!B2:B217,B25) -> 1069868.1
B26: 2025-08 | C26: =SUMIFS('📂 Raw Data'!I2:I217,'📂 Raw Data'!B2:B217,B26) -> 1190366.3 | D26: =SUMIFS('📂 Raw Data'!K2:K217,'📂 Raw Data'!B2:B217,B26) -> 1007024.6 | E26: =SUMIFS('📂 Raw Data'!N2:N217,'📂 Raw Data'!B2:B217,B26) -> 12084295 | F26: =SUMIFS('📂 Raw Data'!O2:O217,'📂 Raw Data'!B2:B217,B26) -> 1007024.6 | G26: =AVERAGEIFS('📂 Raw Data'!J2:J217,'📂 Raw Data'!B2:B217,B26) -> 0.14804444 | H26: =SUMIFS('📂 Raw Data'!L2:L217,'📂 Raw Data'!B2:B217,B26) -> 24969.63 | I26: =SUMIFS('📂 Raw Data'!M2:M217,'📂 Raw Data'!B2:B217,B26) -> 1031994.2
B27: 2025-09 | C27: =SUMIFS('📂 Raw Data'!I2:I217,'📂 Raw Data'!B2:B217,B27) -> 926805.78 | D27: =SUMIFS('📂 Raw Data'!K2:K217,'📂 Raw Data'!B2:B217,B27) -> 836844.97 | E27: =SUMIFS('📂 Raw Data'!N2:N217,'📂 Raw Data'!B2:B217,B27) -> 10042140 | F27: =SUMIFS('📂 Raw Data'!O2:O217,'📂 Raw Data'!B2:B217,B27) -> 836844.97 | G27: =AVERAGEIFS('📂 Raw Data'!J2:J217,'📂 Raw Data'!B2:B217,B27) -> 0.10924444 | H27: =SUMIFS('📂 Raw Data'!L2:L217,'📂 Raw Data'!B2:B217,B27) -> 20326.15 | I27: =SUMIFS('📂 Raw Data'!M2:M217,'📂 Raw Data'!B2:B217,B27) -> 857171.12
B28: 2025-10 | C28: =SUMIFS('📂 Raw Data'!I2:I217,'📂 Raw Data'!B2:B217,B28) -> 829289.25 | D28: =SUMIFS('📂 Raw Data'!K2:K217,'📂 Raw Data'!B2:B217,B28) -> 741254.36 | E28: =SUMIFS('📂 Raw Data'!N2:N217,'📂 Raw Data'!B2:B217,B28) -> 8895052.5 | F28: =SUMIFS('📂 Raw Data'!O2:O217,'📂 Raw Data'!B2:B217,B28) -> 741254.36 | G28: =AVERAGEIFS('📂 Raw Data'!J2:J217,'📂 Raw Data'!B2:B217,B28) -> 0.11273333 | H28: =SUMIFS('📂 Raw Data'!L2:L217,'📂 Raw Data'!B2:B217,B28) -> 59749.01 | I28: =SUMIFS('📂 Raw Data'!M2:M217,'📂 Raw Data'!B2:B217,B28) -> 801003.36
B29: 2025-11 | C29: =SUMIFS('📂 Raw Data'!I2:I217,'📂 Raw Data'!B2:B217,B29) -> 870892.76 | D29: =SUMIFS('📂 Raw Data'!K2:K217,'📂 Raw Data'!B2:B217,B29) -> 812776.58 | E29: =SUMIFS('📂 Raw Data'!N2:N217,'📂 Raw Data'!B2:B217,B29) -> 9753319.1 | F29: =SUMIFS('📂 Raw Data'!O2:O217,'📂 Raw Data'!B2:B217,B29) -> 812776.58 | G29: =AVERAGEIFS('📂 Raw Data'!J2:J217,'📂 Raw Data'!B2:B217,B29) -> 0.072188889 | H29: =SUMIFS('📂 Raw Data'!L2:L217,'📂 Raw Data'!B2:B217,B29) -> 638.33 | I29: =SUMIFS('📂 Raw Data'!M2:M217,'📂 Raw Data'!B2:B217,B29) -> 813414.92
B30: 2025-12 | C30: =SUMIFS('📂 Raw Data'!I2:I217,'📂 Raw Data'!B2:B217,B30) -> 1377227.3 | D30: =SUMIFS('📂 Raw Data'!K2:K217,'📂 Raw Data'!B2:B217,B30) -> 1136099.4 | E30: =SUMIFS('📂 Raw Data'!N2:N217,'📂 Raw Data'!B2:B217,B30) -> 13633193 | F30: =SUMIFS('📂 Raw Data'!O2:O217,'📂 Raw Data'!B2:B217,B30) -> 1136099.4 | G30: =AVERAGEIFS('📂 Raw Data'!J2:J217,'📂 Raw Data'!B2:B217,B30) -> 0.15994444 | H30: =SUMIFS('📂 Raw Data'!L2:L217,'📂 Raw Data'!B2:B217,B30) -> 68431.29 | I30: =SUMIFS('📂 Raw Data'!M2:M217,'📂 Raw Data'!B2:B217,B30) -> 1204530.7
B31: TOTAL / AVERAGE | C31: =SUM(C7:C30) -> 25775590 | D31: =SUM(D7:D30) -> 22598636 | E31: =SUM(E7:E30) -> 2.7118364e+08 | F31: =SUM(F7:F30) -> 22598636 | G31: =AVERAGE(G7:G30) -> 0.11647176 | H31: =SUM(H7:H30) -> 631937.07 | I31: =SUM(I7:I30) -> 23230573
B34: NET REVENUE · Business Unit × Product
B35: Business Unit | C35: Product A | D35: Product B | E35: Product C | F35: Total
B36: APAC | C36: =SUMIFS('📂 Raw Data'!K2:K217,'📂 Raw Data'!C2:C217,B36,'📂 Raw Data'!D2:D217,"Product A") -> 2473552.1 | D36: =SUMIFS('📂 Raw Data'!K2:K217,'📂 Raw Data'!C2:C217,B36,'📂 Raw Data'!D2:D217,"Product B") -> 2805772.3 | E36: =SUMIFS('📂 Raw Data'!K2:K217,'📂 Raw Data'!C2:C217,B36,'📂 Raw Data'!D2:D217,"Product C") -> 2372200.7 | F36: =SUM(C36:E36) -> 7651525.1
B37: Europe | C37: =SUMIFS('📂 Raw Data'!K2:K217,'📂 Raw Data'!C2:C217,B37,'📂 Raw Data'!D2:D217,"Product A") -> 2225581.6 | D37: =SUMIFS('📂 Raw Data'!K2:K217,'📂 Raw Data'!C2:C217,B37,'📂 Raw Data'!D2:D217,"Product B") -> 2907763.2 | E37: =SUMIFS('📂 Raw Data'!K2:K217,'📂 Raw Data'!C2:C217,B37,'📂 Raw Data'!D2:D217,"Product C") -> 1917078.4 | F37: =SUM(C37:E37) -> 7050423.2
B38: North America | C38: =SUMIFS('📂 Raw Data'!K2:K217,'📂 Raw Data'!C2:C217,B38,'📂 Raw Data'!D2:D217,"Product A") -> 2657990.4 | D38: =SUMIFS('📂 Raw Data'!K2:K217,'📂 Raw Data'!C2:C217,B38,'📂 Raw Data'!D2:D217,"Product B") -> 2820177.6 | E38: =SUMIFS('📂 Raw Data'!K2:K217,'📂 Raw Data'!C2:C217,B38,'📂 Raw Data'!D2:D217,"Product C") -> 2418519.9 | F38: =SUM(C38:E38) -> 7896687.9

Sheet 🗺 Dashboard Logic
B2: DASHBOARD LOGIC · KPI Definitions, Metric Rationale & Audience Mapping
B5: KPI / METRIC | C5: DEFINITION | D5: CALCULATION | E5: WHY IT MATTERS | F5: PRIMARY AUDIENCE
B6: Net Revenue | C6: Gross revenue after discounts applied | D6: Gross Revenue × (1 – Discount %) | E6: Primary top-line measure — what the business actually earns after commercial concessions | F6: All audiences
B7: Gross Revenue | C7: Total revenue before any discount reduction | D7: Units Sold × Price per Unit | E7: Establishes the pre-discount baseline; gap to Net Revenue reveals total discount cost | F7: CFO / FP&A
B8: ARR (Annual Recurring Revenue) | C8: Annualised value of recurring revenue contracts | D8: MRR × 12 | E8: Board and investor metric — signals business scale and revenue predictability | F8: CEO / CFO / Board
B9: MRR (Monthly Recurring Revenue) | C9: Monthly recurring contract value | D9: Net Revenue (recurring portion) | E9: Operational recurring revenue signal — used in ARR bridge and churn analysis | F9: CFO / FP&A / Sales
B10: Discount % | C10: Commercial discount applied to gross revenue | D10: 1 – (Net Revenue / Gross Revenue) | E10: Margin risk signal — discounts above 12% compress margin and indicate pricing pressure | F10: CFO / Sales Leadership
B11: Deferred Revenue Δ | C11: Change in revenue recognised in future periods | D11: Recognised Revenue – Net Revenue (net movement) | E11: Revenue quality indicator — positive deferred means future revenue already contracted | F11: CFO / FP&A / Audit
B12: Recognized Revenue | C12: Revenue earned and recognised in the current period | D12: Net Revenue + Deferred Revenue Change | E12: AASB 15 / IFRS 15 reporting metric — what appears on the P&L in the period | F12: CFO / FP&A / Audit
B13: Revenue Mix % | C13: Share of revenue by type (New / Expansion / Renewal) | D13: Segment Revenue / Total Net Revenue | E13: Growth quality signal — Expansion-led growth is healthier than New-customer dependence | F13: CEO / CFO / Sales
B17: KPI × AUDIENCE MAPPING MATRIX
B18: KPI | C18: CEO | D18: CFO | E18: FP&A | F18: Sales | G18: Board
B19: Net Revenue | C19: ✅ | D19: ✅ | E19: ✅ | F19: ✅ | G19: ✅
B20: Gross Revenue | C20: — | D20: ✅ | E20: ✅ | F20: — | G20: —
B21: ARR | C21: ✅ | D21: ✅ | E21: ✅ | F21: — | G21: ✅
B22: MRR | C22: — | D22: ✅ | E22: ✅ | F22: ✅ | G22: —
B23: Discount % | C23: — | D23: ✅ | E23: ✅ | F23: ✅ | G23: ⚠️
B24: Deferred Rev Δ | C24: — | D24: ✅ | E24: ✅ | F24: — | G24: ⚠️
B25: Recognized Rev | C25: — | D25: ✅ | E25: ✅ | F25: — | G25: —
B26: Revenue Mix % | C26: ✅ | D26: ✅ | E26: ✅ | F26: ✅ | G26: ✅

Sheet ✅ QA Control
B2: QA CONTROL · Data Integrity & Reconciliation Checks
B3: All checks run against Raw Data sheet · 13 integrity checks · PASS = no action · FAIL = investigate before publishing
B6: CHECK | C6: EXPECTED | D6: ACTUAL | E6: RESULT | F6: NOTE
B7: Row Count = 216 | C7: 216 | D7: =COUNTA('📂 Raw Data'!B2:B217) -> 216 | E7: =IF(D7=216,"✅ PASS","❌ FAIL") -> ✅ PASS | F7: Row count on Month col B — col A is blank padding, never count col A
B8: Total Gross Revenue | C8: $25,775,590 | D8: =SUM('📂 Raw Data'!I2:I217) -> 25775590 | E8: =IF(ABS(D8-25775590.27)<1,"✅ PASS","⚠️ CHECK") -> ✅ PASS | F8: Gross Revenue col I
B9: Total Net Revenue | C9: $22,598,636 | D9: =SUM('📂 Raw Data'!K2:K217) -> 22598636 | E9: =IF(ABS(D9-22598636.27)<1,"✅ PASS","⚠️ CHECK") -> ✅ PASS | F9: Net Revenue col K — primary top-line check
B10: Avg Discount % within range | C10: 0.08 – 0.18 | D10: =AVERAGE('📂 Raw Data'!J2:J217) -> 0.11647176 | E10: =IF(AND(D10>0.08,D10<0.18),"✅ PASS","⚠️ CHECK") -> ✅ PASS | F10: Discount col J stored as decimal (0.08 = 8%) — check range 8%-18%
B11: ARR ≥ Net Revenue (always) | C11: ARR > Net Rev | D11: =IF(SUM('📂 Raw Data'!N2:N217)>SUM('📂 Raw Data'!K2:K217),"Yes","No") -> Yes | E11: =IF(D11="Yes","✅ PASS","❌ FAIL") -> ✅ PASS | F11: ARR col N vs Net Revenue col K — ARR annualised, always larger
B12: Deferred Revenue — No blanks | C12: 0 blanks | D12: =COUNTBLANK('📂 Raw Data'!L2:L217) -> 0 | E12: =IF(D12=0,"✅ PASS","❌ FAIL") -> ✅ PASS | F12: Deferred Revenue Change col L — no blanks in 216 rows
B13: Currency = USD throughout | C13: 216 | D13: =COUNTIF('📂 Raw Data'!P2:P217,"USD") -> 216 | E13: =IF(D13=216,"✅ PASS","❌ FAIL") -> ✅ PASS | F13: Currency col P — all 216 rows must be USD
B14: Net Revenue < Gross Revenue (always) | C14: 0 violations | D14: =SUMPRODUCT(('📂 Raw Data'!K2:K217>'📂 Raw Data'!I2:I217)*1) -> 0 | E14: =IF(D14=0,"✅ PASS","❌ FAIL — net exceeds gross") -> ✅ PASS | F14: SUMPRODUCT compares Net Revenue col K > Gross Revenue col I row-by-row. Must be 0.
B15: Recognized Revenue reconciliation | C15: ~$23.2M | D15: =SUM('📂 Raw Data'!M2:M217) -> 23230573 | E15: =IF(ABS(D15-23230573.34)<100,"✅ PASS","⚠️ CHECK") -> ✅ PASS | F15: Recognized Revenue col M — AASB 15 check
B16: Date range = Jan 2024 – Dec 2025 | C16: 24 months | D16: =COUNTA(_xlfn.UNIQUE('📂 Raw Data'!B2:B217)) -> 24 | E16: =IF(D16=24,"✅ PASS","⚠️ CHECK") -> ✅ PASS | F16: Unique months in col B — Jan 2024 to Dec 2025 = 24
B17: Discount logic tie-back (sample) | C17: Gap < $500 (rounding tolerance) | D17: {=ROUND(SUMPRODUCT(('📂 Raw Data'!I2:I217)*(1-'📂 Raw Data'!J2:J217))-SUM('📂 Raw Data'!K2:K217),0)} -> -64 | E17: =IF(ABS(D17)<500,"✅ PASS","⚠️ CHECK — discount logic gap") -> ✅ PASS | F17: Gap of -$64 across 216 rows is acceptable rounding — $0.30 per row average. Net Revenue in this dataset was independently stored, not derived directly from Gross × (1 - Disc%). Any gap exceeding $500 warrants investigation.
B18: ARR vs MRR×12 alignment | C18: 0 row deviations | D18: =SUMPRODUCT((ABS('📂 Raw Data'!N2:N217/'📂 Raw Data'!O2:O217-12)>0.01)*1) -> 0 | E18: =IF(D18=0,"✅ PASS","❌ FAIL — ARR/MRR mismatch") -> ✅ PASS | F18: Row-level check: ARR/MRR ratio must equal 12 (±0.01) for every row. Aggregate SUM comparison is unreliable — rounding errors net off and can mask real misalignment. 0 deviations = data is consistent.
B19: Row-Level Audit — FAIL count | C19: 0 failures | D19: =COUNTIF('📂 Raw Data'!Y2:Y217,"❌ FAIL") -> 0 | E19: =IF(D19=0,"✅ PASS","❌ FAIL — see Raw Data col V") -> ✅ PASS | F19: Row-level audit in Raw Data cols R-V: Net Revenue logic, ARR=MRR×12, Recognized bridge, Critical fields complete.

Sheet 📊 Chart Data
A1: CHART DATA · Source tables for all embedded charts
A3: Month | B3: Net Revenue | C3: Gross Revenue | D3: ARR | E3: MRR | F3: Avg Disc % | G3: Deferred Δ
A4: ='📈 Revenue Analysis'!B7 -> 2024-01 | B4: ='📈 Revenue Analysis'!D7 -> 653003.46 | C4: ='📈 Revenue Analysis'!C7 -> 759773.83 | D4: ='📈 Revenue Analysis'!E7 -> 7836041.6 | E4: ='📈 Revenue Analysis'!F7 -> 653003.46 | F4: ='📈 Revenue Analysis'!G7 -> 0.11867778 | G4: ='📈 Revenue Analysis'!H7 -> 14989.52
A5: ='📈 Revenue Analysis'!B8 -> 2024-02 | B5: ='📈 Revenue Analysis'!D8 -> 583177.6 | C5: ='📈 Revenue Analysis'!C8 -> 641991.03 | D5: ='📈 Revenue Analysis'!E8 -> 6998131.2 | E5: ='📈 Revenue Analysis'!F8 -> 583177.6 | F5: ='📈 Revenue Analysis'!G8 -> 0.097355556 | G5: ='📈 Revenue Analysis'!H8 -> 2686.46
A6: ='📈 Revenue Analysis'!B9 -> 2024-03 | B6: ='📈 Revenue Analysis'!D9 -> 1059808 | C6: ='📈 Revenue Analysis'!C9 -> 1151682.1 | D6: ='📈 Revenue Analysis'!E9 -> 12717696 | E6: ='📈 Revenue Analysis'!F9 -> 1059808 | F6: ='📈 Revenue Analysis'!G9 -> 0.086166667 | G6: ='📈 Revenue Analysis'!H9 -> 41833.94
A7: ='📈 Revenue Analysis'!B10 -> 2024-04 | B7: ='📈 Revenue Analysis'!D10 -> 973180.27 | C7: ='📈 Revenue Analysis'!C10 -> 1135182.7 | D7: ='📈 Revenue Analysis'!E10 -> 11678163 | E7: ='📈 Revenue Analysis'!F10 -> 973180.27 | F7: ='📈 Revenue Analysis'!G10 -> 0.14396667 | G7: ='📈 Revenue Analysis'!H10 -> 43722.63
A8: ='📈 Revenue Analysis'!B11 -> 2024-05 | B8: ='📈 Revenue Analysis'!D11 -> 965325.7 | C8: ='📈 Revenue Analysis'!C11 -> 1064439.3 | D8: ='📈 Revenue Analysis'!E11 -> 11583908 | E8: ='📈 Revenue Analysis'!F11 -> 965325.7 | F8: ='📈 Revenue Analysis'!G11 -> 0.0775 | G8: ='📈 Revenue Analysis'!H11 -> 16162.46
A9: ='📈 Revenue Analysis'!B12 -> 2024-06 | B9: ='📈 Revenue Analysis'!D12 -> 692527.11 | C9: ='📈 Revenue Analysis'!C12 -> 777405.83 | D9: ='📈 Revenue Analysis'!E12 -> 8310325.4 | E9: ='📈 Revenue Analysis'!F12 -> 692527.11 | F9: ='📈 Revenue Analysis'!G12 -> 0.1111 | G9: ='📈 Revenue Analysis'!H12 -> 26325.99
A10: ='📈 Revenue Analysis'!B13 -> 2024-07 | B10: ='📈 Revenue Analysis'!D13 -> 1218456.7 | C10: ='📈 Revenue Analysis'!C13 -> 1371764.6 | D10: ='📈 Revenue Analysis'!E13 -> 14621481 | E10: ='📈 Revenue Analysis'!F13 -> 1218456.7 | F10: ='📈 Revenue Analysis'!G13 -> 0.1113 | G10: ='📈 Revenue Analysis'!H13 -> -649.53
A11: ='📈 Revenue Analysis'!B14 -> 2024-08 | B11: ='📈 Revenue Analysis'!D14 -> 637601.64 | C11: ='📈 Revenue Analysis'!C14 -> 738981.86 | D11: ='📈 Revenue Analysis'!E14 -> 7651219.5 | E11: ='📈 Revenue Analysis'!F14 -> 637601.64 | F11: ='📈 Revenue Analysis'!G14 -> 0.12441111 | G11: ='📈 Revenue Analysis'!H14 -> 4066.02
A12: ='📈 Revenue Analysis'!B15 -> 2024-09 | B12: ='📈 Revenue Analysis'!D15 -> 1568177.1 | C12: ='📈 Revenue Analysis'!C15 -> 1835974.7 | D12: ='📈 Revenue Analysis'!E15 -> 18818125 | E12: ='📈 Revenue Analysis'!F15 -> 1568177.1 | F12: ='📈 Revenue Analysis'!G15 -> 0.1223 | G12: ='📈 Revenue Analysis'!H15 -> 46928.9
A13: ='📈 Revenue Analysis'!B16 -> 2024-10 | B13: ='📈 Revenue Analysis'!D16 -> 776190.31 | C13: ='📈 Revenue Analysis'!C16 -> 912231.09 | D13: ='📈 Revenue Analysis'!E16 -> 9314283.8 | E13: ='📈 Revenue Analysis'!F16 -> 776190.31 | F13: ='📈 Revenue Analysis'!G16 -> 0.12925556 | G13: ='📈 Revenue Analysis'!H16 -> 21344.56
A14: ='📈 Revenue Analysis'!B17 -> 2024-11 | B14: ='📈 Revenue Analysis'!D17 -> 882368.33 | C14: ='📈 Revenue Analysis'!C17 -> 959174.15 | D14: ='📈 Revenue Analysis'!E17 -> 10588420 | E14: ='📈 Revenue Analysis'!F17 -> 882368.33 | F14: ='📈 Revenue Analysis'!G17 -> 0.087077778 | G14: ='📈 Revenue Analysis'!H17 -> 10759.52
A15: ='📈 Revenue Analysis'!B18 -> 2024-12 | B15: ='📈 Revenue Analysis'!D18 -> 1104736.4 | C15: ='📈 Revenue Analysis'!C18 -> 1248081.6 | D15: ='📈 Revenue Analysis'!E18 -> 13256836 | E15: ='📈 Revenue Analysis'!F18 -> 1104736.4 | F15: ='📈 Revenue Analysis'!G18 -> 0.10112222 | G15: ='📈 Revenue Analysis'!H18 -> 13578.94
... A27: ='📈 Revenue Analysis'!B30 -> 2025-12 | B27: ='📈 Revenue Analysis'!D30 -> 1136099.4 | C27: ='📈 Revenue Analysis'!C30 -> 1377227.3 | D27: ='📈 Revenue Analysis'!E30 -> 13633193 | E27: ='📈 Revenue Analysis'!F30 -> 1136099.4 | F27: ='📈 Revenue Analysis'!G30 -> 0.15994444 | G27: ='📈 Revenue Analysis'!H30 -> 68431.29
A29: Business Unit | B29: Net Revenue
A30: ='📈 Revenue Analysis'!B38 -> North America | B30: ='📈 Revenue Analysis'!F38 -> 7896687.9
A31: ='📈 Revenue Analysis'!B36 -> APAC | B31: ='📈 Revenue Analysis'!F36 -> 7651525.1
A32: ='📈 Revenue Analysis'!B37 -> Europe | B32: ='📈 Revenue Analysis'!F37 -> 7050423.2
A35: Customer Segment | B35: Avg Discount %
A36: Enterprise | B36: =AVERAGEIFS('📂 Raw Data'!J2:J217,'📂 Raw Data'!F2:F217,"Enterprise") -> 0.12048649
A37: Mid-Market | B37: =AVERAGEIFS('📂 Raw Data'!J2:J217,'📂 Raw Data'!F2:F217,"Mid-Market") -> 0.10937838
A38: SMB | B38: =AVERAGEIFS('📂 Raw Data'!J2:J217,'📂 Raw Data'!F2:F217,"SMB") -> 0.11982206

Sheet 📉 Charts
B1: CHARTS · Revenue Momentum, Business Unit Mix, ARR/MRR Trend, Discount Risk
B3: All charts pull live from Chart Data sheet — update Raw Data to refresh

Sheet 📂 Raw Data
B1: Month | C1: Business Unit | D1: Product | E1: Revenue Type | F1: Customer Segment | G1: Units Sold | H1: Price per Unit | I1: Gross Revenue | J1: Discount (%) | K1: Net Revenue | L1: Deferred Revenue Change | M1: Recognized Revenue | N1: ARR | O1: MRR | P1: Currency | Q1: Month_dt | R1: Year | S1: MonthNum | U1: ✔ Net Rev Check | V1: ✔ ARR = MRR×12 | W1: ✔ Recognized Bridge | X1: ✔ Critical Fields | Y1: ⚑ Row Status
B2: 2024-01 | C2: North America | D2: Product A | E2: Renewal | F2: Enterprise | G2: 110 | H2: 433.34 | I2: 47667.6 | J2: 0.0835 | K2: 43687.64 | L2: 5516.06 | M2: 49203.7 | N2: 524251.71 | O2: 43687.64 | P2: USD | Q2: 45292 | R2: 2024 | S2: 1 | U2: =IF(I2=0,"N/A",ABS(I2*(1-J2)-K2)/I2<0.001) -> TRUE | V2: =ABS(N2-O2*12)<=1 -> TRUE | W2: =ABS(K2+L2-M2)<=1 -> TRUE | X2: =AND(B2<>"",C2<>"",K2<>0,N2<>0) -> TRUE | Y2: =IF(AND(OR(U2=TRUE(),U2="N/A"),V2=TRUE(),W2=TRUE(),X2=TRUE()),"✅ PASS","❌ FAIL") -> ✅ PASS
B3: 2024-01 | C3: North America | D3: Product B | E3: Renewal | F3: Enterprise | G3: 200 | H3: 238.48 | I3: 47695.65 | J3: 0.007 | K3: 47363.72 | L3: -593.75 | M3: 46769.97 | N3: 568364.62 | O3: 47363.72 | P3: USD | Q3: 45292 | R3: 2024 | S3: 1 | U3: =IF(I3=0,"N/A",ABS(I3*(1-J3)-K3)/I3<0.001) -> TRUE | V3: =ABS(N3-O3*12)<=1 -> TRUE | W3: =ABS(K3+L3-M3)<=1 -> TRUE | X3: =AND(B3<>"",C3<>"",K3<>0,N3<>0) -> TRUE | Y3: =IF(AND(OR(U3=TRUE(),U3="N/A"),V3=TRUE(),W3=TRUE(),X3=TRUE()),"✅ PASS","❌ FAIL") -> ✅ PASS
B4: 2024-01 | C4: North America | D4: Product C | E4: Expansion | F4: SMB | G4: 160 | H4: 282.74 | I4: 45238.07 | J4: 0.1617 | K4: 37921.36 | L4: 1531.35 | M4: 39452.71 | N4: 455056.36 | O4: 37921.36 | P4: USD | Q4: 45292 | R4: 2024 | S4: 1 | U4: =IF(I4=0,"N/A",ABS(I4*(1-J4)-K4)/I4<0.001) -> TRUE | V4: =ABS(N4-O4*12)<=1 -> TRUE | W4: =ABS(K4+L4-M4)<=1 -> TRUE | X4: =AND(B4<>"",C4<>"",K4<>0,N4<>0) -> TRUE | Y4: =IF(AND(OR(U4=TRUE(),U4="N/A"),V4=TRUE(),W4=TRUE(),X4=TRUE()),"✅ PASS","❌ FAIL") -> ✅ PASS
B5: 2024-01 | C5: Europe | D5: Product A | E5: New | F5: Enterprise | G5: 61 | H5: 923.33 | I5: 56323.19 | J5: 0.047 | K5: 53673.78 | L5: 7746.1 | M5: 61419.88 | N5: 644085.32 | O5: 53673.78 | P5: USD | Q5: 45292 | R5: 2024 | S5: 1 | U5: =IF(I5=0,"N/A",ABS(I5*(1-J5)-K5)/I5<0.001) -> TRUE | V5: =ABS(N5-O5*12)<=1 -> TRUE | W5: =ABS(K5+L5-M5)<=1 -> TRUE | X5: =AND(B5<>"",C5<>"",K5<>0,N5<>0) -> TRUE | Y5: =IF(AND(OR(U5=TRUE(),U5="N/A"),V5=TRUE(),W5=TRUE(),X5=TRUE()),"✅ PASS","❌ FAIL") -> ✅ PASS
B6: 2024-01 | C6: Europe | D6: Product B | E6: Renewal | F6: Enterprise | G6: 256 | H6: 760.23 | I6: 194618.79 | J6: 0.1887 | K6: 157895.81 | L6: 6840.98 | M6: 164736.79 | N6: 1894749.8 | O6: 157895.81 | P6: USD | Q6: 45292 | R6: 2024 | S6: 1 | U6: =IF(I6=0,"N/A",ABS(I6*(1-J6)-K6)/I6<0.001) -> TRUE | V6: =ABS(N6-O6*12)<=1 -> TRUE | W6: =ABS(K6+L6-M6)<=1 -> TRUE | X6: =AND(B6<>"",C6<>"",K6<>0,N6<>0) -> TRUE | Y6: =IF(AND(OR(U6=TRUE(),U6="N/A"),V6=TRUE(),W6=TRUE(),X6=TRUE()),"✅ PASS","❌ FAIL") -> ✅ PASS
B7: 2024-01 | C7: Europe | D7: Product C | E7: New | F7: Mid-Market | G7: 227 | H7: 350.25 | I7: 79506.76 | J7: 0.0654 | K7: 74305.12 | L7: 1140.43 | M7: 75445.56 | N7: 891661.48 | O7: 74305.12 | P7: USD | Q7: 45292 | R7: 2024 | S7: 1 | U7: =IF(I7=0,"N/A",ABS(I7*(1-J7)-K7)/I7<0.001) -> TRUE | V7: =ABS(N7-O7*12)<=1 -> TRUE | W7: =ABS(K7+L7-M7)<=1 -> TRUE | X7: =AND(B7<>"",C7<>"",K7<>0,N7<>0) -> TRUE | Y7: =IF(AND(OR(U7=TRUE(),U7="N/A"),V7=TRUE(),W7=TRUE(),X7=TRUE()),"✅ PASS","❌ FAIL") -> ✅ PASS
B8: 2024-01 | C8: APAC | D8: Product A | E8: Expansion | F8: Mid-Market | G8: 195 | H8: 583.64 | I8: 113809.71 | J8: 0.2435 | K8: 86092.9 | L8: -3596.69 | M8: 82496.2 | N8: 1033114.8 | O8: 86092.9 | P8: USD | Q8: 45292 | R8: 2024 | S8: 1 | U8: =IF(I8=0,"N/A",ABS(I8*(1-J8)-K8)/I8<0.001) -> TRUE | V8: =ABS(N8-O8*12)<=1 -> TRUE | W8: =ABS(K8+L8-M8)<=1 -> TRUE | X8: =AND(B8<>"",C8<>"",K8<>0,N8<>0) -> TRUE | Y8: =IF(AND(OR(U8=TRUE(),U8="N/A"),V8=TRUE(),W8=TRUE(),X8=TRUE()),"✅ PASS","❌ FAIL") -> ✅ PASS
B9: 2024-01 | C9: APAC | D9: Product B | E9: Renewal | F9: SMB | G9: 103 | H9: 914.43 | I9: 94186.23 | J9: 0.0705 | K9: 87548.64 | L9: -371.14 | M9: 87177.5 | N9: 1050583.7 | O9: 87548.64 | P9: USD | Q9: 45292 | R9: 2024 | S9: 1 | U9: =IF(I9=0,"N/A",ABS(I9*(1-J9)-K9)/I9<0.001) -> TRUE | V9: =ABS(N9-O9*12)<=1 -> TRUE | W9: =ABS(K9+L9-M9)<=1 -> TRUE | X9: =AND(B9<>"",C9<>"",K9<>0,N9<>0) -> TRUE | Y9: =IF(AND(OR(U9=TRUE(),U9="N/A"),V9=TRUE(),W9=TRUE(),X9=TRUE()),"✅ PASS","❌ FAIL") -> ✅ PASS
B10: 2024-01 | C10: APAC | D10: Product C | E10: Renewal | F10: SMB | G10: 79 | H10: 1021.87 | I10: 80727.83 | J10: 0.2008 | K10: 64514.49 | L10: -3223.82 | M10: 61290.67 | N10: 774173.92 | O10: 64514.49 | P10: USD | Q10: 45292 | R10: 2024 | S10: 1 | U10: =IF(I10=0,"N/A",ABS(I10*(1-J10)-K10)/I10<0.001) -> TRUE | V10: =ABS(N10-O10*12)<=1 -> TRUE | W10: =ABS(K10+L10-M10)<=1 -> TRUE | X10: =AND(B10<>"",C10<>"",K10<>0,N10<>0) -> TRUE | Y10: =IF(AND(OR(U10=TRUE(),U10="N/A"),V10=TRUE(),W10=TRUE(),X10=TRUE()),"✅ PASS","❌ FAIL") -> ✅ PASS
B11: 2024-02 | C11: North America | D11: Product A | E11: New | F11: Enterprise | G11: 202 | H11: 583.94 | I11: 117955.8 | J11: 0.0033 | K11: 117567.93 | L11: 3022.56 | M11: 120590.49 | N11: 1410815.2 | O11: 117567.93 | P11: USD | Q11: 45323 | R11: 2024 | S11: 2 | U11: =IF(I11=0,"N/A",ABS(I11*(1-J11)-K11)/I11<0.001) -> TRUE | V11: =ABS(N11-O11*12)<=1 -> TRUE | W11: =ABS(K11+L11-M11)<=1 -> TRUE | X11: =AND(B11<>"",C11<>"",K11<>0,N11<>0) -> TRUE | Y11: =IF(AND(OR(U11=TRUE(),U11="N/A"),V11=TRUE(),W11=TRUE(),X11=TRUE()),"✅ PASS","❌ FAIL") -> ✅ PASS
B12: 2024-02 | C12: North America | D12: Product B | E12: New | F12: Mid-Market | G12: 111 | H12: 870.76 | I12: 96653.86 | J12: 0.084 | K12: 88532.45 | L12: -564.47 | M12: 87967.98 | N12: 1062389.4 | O12: 88532.45 | P12: USD | Q12: 45323 | R12: 2024 | S12: 2 | U12: =IF(I12=0,"N/A",ABS(I12*(1-J12)-K12)/I12<0.001) -> TRUE | V12: =ABS(N12-O12*12)<=1 -> TRUE | W12: =ABS(K12+L12-M12)<=1 -> TRUE | X12: =AND(B12<>"",C12<>"",K12<>0,N12<>0) -> TRUE | Y12: =IF(AND(OR(U12=TRUE(),U12="N/A"),V12=TRUE(),W12=TRUE(),X12=TRUE()),"✅ PASS","❌ FAIL") -> ✅ PASS
B13: 2024-02 | C13: North America | D13: Product C | E13: New | F13: Mid-Market | G13: 144 | H13: 691.5 | I13: 99576.53 | J13: 0.1356 | K13: 86076.3 | L13: -7274.36 | M13: 78801.95 | N13: 1032915.7 | O13: 86076.3 | P13: USD | Q13: 45323 | R13: 2024 | S13: 2 | U13: =IF(I13=0,"N/A",ABS(I13*(1-J13)-K13)/I13<0.001) -> TRUE | V13: =ABS(N13-O13*12)<=1 -> TRUE | W13: =ABS(K13+L13-M13)<=1 -> TRUE | X13: =AND(B13<>"",C13<>"",K13<>0,N13<>0) -> TRUE | Y13: =IF(AND(OR(U13=TRUE(),U13="N/A"),V13=TRUE(),W13=TRUE(),X13=TRUE()),"✅ PASS","❌ FAIL") -> ✅ PASS
... B217: 2025-12 | C217: APAC | D217: Product C | E217: Expansion | F217: Enterprise | G217: 289 | H217: 769.49 | I217: 222382.4 | J217: 0.1806 | K217: 182222.13 | L217: 1096.61 | M217: 183318.74 | N217: 2186665.5 | O217: 182222.13 | P217: USD | Q217: 45992 | R217: 2025 | S217: 12 | U217: =IF(I217=0,"N/A",ABS(I217*(1-J217)-K217)/I217<0.001) -> TRUE | V217: =ABS(N217-O217*12)<=1 -> TRUE | W217: =ABS(K217+L217-M217)<=1 -> TRUE | X217: =AND(B217<>"",C217<>"",K217<>0,N217<>0) -> TRUE | Y217: =IF(AND(OR(U217=TRUE(),U217="N/A"),V217=TRUE(),W217=TRUE(),X217=TRUE()),"✅ PASS","❌ FAIL") -> ✅ PASS
U220: AUDIT SUMMARY
U221: Total Rows | Y221: =COUNTA(B2:B217) -> 216
U222: ✅ PASS Rows | Y222: =COUNTIF(Y2:Y217,"✅ PASS") -> 216
U223: ❌ FAIL Rows | Y223: =COUNTIF(Y2:Y217,"❌ FAIL") -> 0

Sheet QA_ValidationModule
A1: Month | B1: Business Unit | C1: Product | D1: Revenue Type | E1: Customer Segment | F1: Units Sold | G1: Price per Unit | H1: Gross Revenue | I1: Discount (%) | J1: _Computed_Gross | K1: _Gap_Gross | L1: Net Revenue | M1: _Computed_Net | N1: _Gap_Net | O1: Deferred Revenue Change | P1: Recognized Revenue | Q1: _Computed_Recognized | R1: _Gap_Recognized | S1: ARR | T1: MRR | U1: _Computed_ARR | V1: _Gap_ARR | W1: Check_Gross_Revenue | X1: Check_Net_Revenue | Y1: Check_Recognized_Bridge | Z1: Check_ARR_MRR | AA1: Check_Critical_Fields | AB1: Row_Status | AC1: Failure_Reason
A2: 2024-01 | B2: North America | C2: Product A | D2: Renewal | E2: Enterprise | F2: 110 | G2: 433.34 | H2: 47667.6 | I2: 0.0835 | J2: 47667.4 | K2: 0.2 | L2: 43687.64 | M2: 43687.355 | N2: 0.2846 | O2: 5516.06 | P2: 49203.7 | Q2: 49203.7 | R2: 0 | S2: 524251.71 | T2: 43687.64 | U2: 524251.68 | V2: 0.03 | W2: TRUE | X2: TRUE | Y2: TRUE | Z2: TRUE | AA2: TRUE | AB2: PASS | AC2: No issues
A3: 2024-01 | B3: North America | C3: Product B | D3: Renewal | E3: Enterprise | F3: 200 | G3: 238.48 | H3: 47695.65 | I3: 0.007 | J3: 47696 | K3: 0.35 | L3: 47363.72 | M3: 47361.78 | N3: 1.93955 | O3: -593.75 | P3: 46769.97 | Q3: 46769.97 | R3: 0 | S3: 568364.62 | T3: 47363.72 | U3: 568364.64 | V3: 0.02 | W3: TRUE | X3: TRUE | Y3: TRUE | Z3: TRUE | AA3: TRUE | AB3: PASS | AC3: No issues
A4: 2024-01 | B4: North America | C4: Product C | D4: Expansion | E4: SMB | F4: 160 | G4: 282.74 | H4: 45238.07 | I4: 0.1617 | J4: 45238.4 | K4: 0.33 | L4: 37921.36 | M4: 37923.074 | N4: 1.714081 | O4: 1531.35 | P4: 39452.71 | Q4: 39452.71 | R4: 0 | S4: 455056.36 | T4: 37921.36 | U4: 455056.32 | V4: 0.04 | W4: TRUE | X4: TRUE | Y4: TRUE | Z4: TRUE | AA4: TRUE | AB4: PASS | AC4: No issues
A5: 2024-01 | B5: Europe | C5: Product A | D5: New | E5: Enterprise | F5: 61 | G5: 923.33 | H5: 56323.19 | I5: 0.047 | J5: 56323.13 | K5: 0.06 | L5: 53673.78 | M5: 53676 | N5: 2.22007 | O5: 7746.1 | P5: 61419.88 | Q5: 61419.88 | R5: 0 | S5: 644085.32 | T5: 53673.78 | U5: 644085.36 | V5: 0.04 | W5: TRUE | X5: TRUE | Y5: TRUE | Z5: TRUE | AA5: TRUE | AB5: PASS | AC5: No issues
A6: 2024-01 | B6: Europe | C6: Product B | D6: Renewal | E6: Enterprise | F6: 256 | G6: 760.23 | H6: 194618.79 | I6: 0.1887 | J6: 194618.88 | K6: 0.09 | L6: 157895.81 | M6: 157894.22 | N6: 1.585673 | O6: 6840.98 | P6: 164736.79 | Q6: 164736.79 | R6: 0 | S6: 1894749.8 | T6: 157895.81 | U6: 1894749.7 | V6: 0.06 | W6: TRUE | X6: TRUE | Y6: TRUE | Z6: TRUE | AA6: TRUE | AB6: PASS | AC6: No issues
A7: 2024-01 | B7: Europe | C7: Product C | D7: New | E7: Mid-Market | F7: 227 | G7: 350.25 | H7: 79506.76 | I7: 0.0654 | J7: 79506.75 | K7: 0.01 | L7: 74305.12 | M7: 74307.018 | N7: 1.897896 | O7: 1140.43 | P7: 75445.56 | Q7: 75445.55 | R7: 0.01 | S7: 891661.48 | T7: 74305.12 | U7: 891661.44 | V7: 0.04 | W7: TRUE | X7: TRUE | Y7: TRUE | Z7: TRUE | AA7: TRUE | AB7: PASS | AC7: No issues
A8: 2024-01 | B8: APAC | C8: Product A | D8: Expansion | E8: Mid-Market | F8: 195 | G8: 583.64 | H8: 113809.71 | I8: 0.2435 | J8: 113809.8 | K8: 0.09 | L8: 86092.9 | M8: 86097.046 | N8: 4.145615 | O8: -3596.69 | P8: 82496.2 | Q8: 82496.21 | R8: 0.01 | S8: 1033114.8 | T8: 86092.9 | U8: 1033114.8 | V8: 0.05 | W8: TRUE | X8: TRUE | Y8: TRUE | Z8: TRUE | AA8: TRUE | AB8: PASS | AC8: No issues
A9: 2024-01 | B9: APAC | C9: Product B | D9: Renewal | E9: SMB | F9: 103 | G9: 914.43 | H9: 94186.23 | I9: 0.0705 | J9: 94186.29 | K9: 0.06 | L9: 87548.64 | M9: 87546.101 | N9: 2.539215 | O9: -371.14 | P9: 87177.5 | Q9: 87177.5 | R9: 0 | S9: 1050583.7 | T9: 87548.64 | U9: 1050583.7 | V9: 0.02 | W9: TRUE | X9: TRUE | Y9: TRUE | Z9: TRUE | AA9: TRUE | AB9: PASS | AC9: No issues
A10: 2024-01 | B10: APAC | C10: Product C | D10: Renewal | E10: SMB | F10: 79 | G10: 1021.87 | H10: 80727.83 | I10: 0.2008 | J10: 80727.73 | K10: 0.1 | L10: 64514.49 | M10: 64517.682 | N10: 3.191736 | O10: -3223.82 | P10: 61290.67 | Q10: 61290.67 | R10: 0 | S10: 774173.92 | T10: 64514.49 | U10: 774173.88 | V10: 0.04 | W10: TRUE | X10: TRUE | Y10: TRUE | Z10: TRUE | AA10: TRUE | AB10: PASS | AC10: No issues
A11: 2024-02 | B11: APAC | C11: Product C | D11: Expansion | E11: Mid-Market | F11: 135 | G11: 506.56 | H11: 68386.18 | I11: 0.0443 | J11: 68385.6 | K11: 0.58 | L11: 65359.54 | M11: 65356.672 | N11: 2.867774 | O11: 1985.35 | P11: 67344.88 | Q11: 67344.89 | R11: 0.01 | S11: 784314.43 | T11: 65359.54 | U11: 784314.48 | V11: 0.05 | W11: TRUE | X11: TRUE | Y11: TRUE | Z11: TRUE | AA11: TRUE | AB11: PASS | AC11: No issues
A12: 2024-02 | B12: APAC | C12: Product B | D12: New | E12: Enterprise | F12: 157 | G12: 453.46 | H12: 71193.73 | I12: 0.1497 | J12: 71193.22 | K12: 0.51 | L12: 60532.64 | M12: 60536.029 | N12: 3.388619 | O12: -5209 | P12: 55323.63 | Q12: 55323.64 | R12: 0.01 | S12: 726391.65 | T12: 60532.64 | U12: 726391.68 | V12: 0.03 | W12: TRUE | X12: TRUE | Y12: TRUE | Z12: TRUE | AA12: TRUE | AB12: PASS | AC12: No issues
A13: 2024-02 | B13: APAC | C13: Product A | D13: Expansion | E13: Enterprise | F13: 115 | G13: 381.04 | H13: 43819.72 | I13: 0.2487 | J13: 43819.6 | K13: 0.12 | L13: 32922.36 | M13: 32921.756 | N13: 0.604364 | O13: 4530.83 | P13: 37453.19 | Q13: 37453.19 | R13: 0 | S13: 395068.32 | T13: 32922.36 | U13: 395068.32 | V13: 0 | W13: TRUE | X13: TRUE | Y13: TRUE | Z13: TRUE | AA13: TRUE | AB13: PASS | AC13: No issues
... A217: 2025-12 | B217: APAC | C217: Product C | D217: Expansion | E217: Enterprise | F217: 289 | G217: 769.49 | H217: 222382.4 | I217: 0.1806 | J217: 222382.61 | K217: 0.21 | L217: 182222.13 | M217: 182220.14 | N217: 1.99144 | O217: 1096.61 | P217: 183318.74 | Q217: 183318.74 | R217: 0 | S217: 2186665.5 | T217: 182222.13 | U217: 2186665.6 | V217: 0.04 | W217: TRUE | X217: TRUE | Y217: TRUE | Z217: TRUE | AA217: TRUE | AB217: PASS | AC217: No issues

Sheet QA_AuditSummary
A1: Check | B1: Total_Rows | C1: Pass | D1: Fail | E1: Pass_Rate | F1: Status
A2: Overall Row Status | B2: 216 | C2: 216 | D2: 0 | E2: 1 | F2: CLEAN
A3: Gross Revenue Logic | B3: 216 | C3: 216 | D3: 0 | E3: 1 | F3: CLEAN
A4: Net Revenue Logic | B4: 216 | C4: 216 | D4: 0 | E4: 1 | F4: CLEAN
A5: Recognized Revenue Bridge | B5: 216 | C5: 216 | D5: 0 | E5: 1 | F5: CLEAN
A6: ARR = MRR x 12 | B6: 216 | C6: 216 | D6: 0 | E6: 1 | F6: CLEAN
A7: Critical Fields Complete | B7: 216 | C7: 216 | D7: 0 | E7: 1 | F7: CLEAN

Sheet Monthly_Summary
A1: Month | B1: Gross Revenue | C1: Net Revenue | D1: ARR | E1: MRR | F1: Avg Discount Pct | G1: Deferred Rev Change | H1: Recognized Revenue | I1: Units Sold | J1: MoM Net Rev Change | K1: MoM Net Rev Pct
A2: 2024-01 | B2: 759773.83 | C2: 653003.46 | D2: 7836041.6 | E2: 653003.46 | F2: 0.11867778 | G2: 14989.52 | H2: 667992.98 | I2: 1391
A3: 2024-02 | B3: 641991.03 | C3: 583177.6 | D3: 6998131.2 | E3: 583177.6 | F3: 0.097355556 | G3: 2686.46 | H3: 585864.05 | I3: 1125 | J3: -69825.86 | K3: -0.10693031
A4: 2024-03 | B4: 1151682.1 | C4: 1059808 | D4: 12717696 | E4: 1059808 | F4: 0.086166667 | G4: 41833.94 | H4: 1101641.9 | I4: 1431 | J4: 476630.37 | K4: 0.81729883
A5: 2024-04 | B5: 1135182.7 | C5: 973180.27 | D5: 11678163 | E5: 973180.27 | F5: 0.14396667 | G5: 43722.63 | H5: 1016902.9 | I5: 1571 | J5: -86627.7 | K5: -0.081739053
A6: 2024-05 | B6: 1064439.3 | C6: 965325.7 | D6: 11583908 | E6: 965325.7 | F6: 0.0775 | G6: 16162.46 | H6: 981488.15 | I6: 1666 | J6: -7854.57 | K6: -0.0080710329
A7: 2024-06 | B7: 777405.83 | C7: 692527.11 | D7: 8310325.4 | E7: 692527.11 | F7: 0.1111 | G7: 26325.99 | H7: 718853.12 | I7: 1321 | J7: -272798.59 | K7: -0.28259746
A8: 2024-07 | B8: 1371764.6 | C8: 1218456.7 | D8: 14621481 | E8: 1218456.7 | F8: 0.1113 | G8: -649.53 | H8: 1217807.2 | I8: 1610 | J8: 525929.6 | K8: 0.7594354
A9: 2024-08 | B9: 738981.86 | C9: 637601.64 | D9: 7651219.5 | E9: 637601.64 | F9: 0.12441111 | G9: 4066.02 | H9: 641667.66 | I9: 1344 | J9: -580855.07 | K9: -0.47671375
A10: 2024-09 | B10: 1835974.7 | C10: 1568177.1 | D10: 18818125 | E10: 1568177.1 | F10: 0.1223 | G10: 46928.9 | H10: 1615105.9 | I10: 1984 | J10: 930575.41 | K10: 1.4594934
A11: 2024-10 | B11: 912231.09 | C11: 776190.31 | D11: 9314283.8 | E11: 776190.31 | F11: 0.12925556 | G11: 21344.56 | H11: 797534.87 | I11: 1342 | J11: -791986.74 | K11: -0.50503656
A12: 2024-11 | B12: 959174.15 | C12: 882368.33 | D12: 10588420 | E12: 882368.33 | F12: 0.087077778 | G12: 10759.52 | H12: 893127.83 | I12: 1776 | J12: 106178.02 | K12: 0.1367938
A13: 2024-12 | B13: 1248081.6 | C13: 1104736.4 | D13: 13256836 | E13: 1104736.4 | F13: 0.10112222 | G13: 13578.94 | H13: 1118315.3 | I13: 1993 | J13: 222368.03 | K13: 0.25201271
A14: 2025-01 | B14: 1199518.8 | C14: 1051419.4 | D14: 12617032 | E14: 1051419.4 | F14: 0.12586667 | G14: 74240.55 | H14: 1125659.9 | I14: 1557 | J14: -53317 | K14: -0.048262194
... A25: 2025-12 | B25: 1377227.3 | C25: 1136099.4 | D25: 13633193 | E25: 1136099.4 | F25: 0.15994444 | G25: 68431.29 | H25: 1204530.7 | I25: 1804 | J25: 323322.85 | K25: 0.3978004

Sheet BU_Product_Summary
A1: Business Unit | B1: Product | C1: Net Revenue | D1: Gross Revenue | E1: Units Sold | F1: Avg Discount % | G1: % of Total Net Revenue
A2: APAC | B2: Product B | C2: 2805772.3 | D2: 3235669.7 | E2: 4615 | F2: 0.12571667 | G2: 0.12415671
A3: APAC | B3: Product A | C3: 2473552.1 | D3: 2874240.8 | E3: 4248 | F3: 0.12869167 | G3: 0.10945581
A4: APAC | B4: Product C | C4: 2372200.7 | D4: 2655805.1 | E4: 4145 | F4: 0.10228333 | G4: 0.10497097
A5: Europe | B5: Product B | C5: 2907763.2 | D5: 3290315.8 | E5: 4399 | F5: 0.11724583 | G5: 0.12866985
A6: Europe | B6: Product A | C6: 2225581.6 | D6: 2593540.9 | E6: 3998 | F6: 0.13889167 | G6: 0.098483006
A7: Europe | B7: Product C | C7: 1917078.4 | D7: 2132058.8 | E7: 3632 | F7: 0.10508333 | G7: 0.084831595
A8: North America | B8: Product B | C8: 2820177.6 | D8: 3265015.1 | E8: 4210 | F8: 0.10370417 | G8: 0.12479415
A9: North America | B9: Product A | C9: 2657990.4 | D9: 2970796.2 | E9: 4497 | F9: 0.1167875 | G9: 0.11761729
A10: North America | B10: Product C | C10: 2418519.9 | D10: 2758148 | E10: 4155 | F10: 0.10984167 | G10: 0.10702061

Sheet Segment_Discount_Summary
A1: Customer Segment | B1: Avg Discount Pct | C1: Total Gross Rev | D1: Total Net Rev | E1: Row Count | F1: Total Discount Amount | G1: Discount as Pct of Gross | H1: Risk Flag | I1: Risk Note
A2: Enterprise | B2: 0.12048649 | C2: 9143295.7 | D2: 7964772.3 | E2: 74 | F2: 1178523.3 | G2: 0.12889481 | H2: HIGH | I2: Both avg discount and total discount as % of gross exceed 12% threshold
A3: SMB | B3: 0.11982206 | C3: 8136963.2 | D3: 7112830.6 | E3: 68 | F3: 1024132.6 | G3: 0.12586177 | H3: HIGH | I3: Total discount as % of gross exceeds 12% threshold
A4: Mid-Market | B4: 0.10937838 | C4: 8495331.4 | D4: 7521033.3 | E4: 74 | F4: 974298.08 | G4: 0.11468629 | H4: OK | I4: Within acceptable range
